{
  "schemaVersion": 1,
  "id": "vortexclient",
  "version": "1.0.0",
  "name": "VortexClient",
  "description": "CheatClient",
  "authors": [],
  "contact": {},
  "license": "All-Rights-Reserved",
  "icon": "assets/vortexclient/icon.png",
  "environment": "client",
  "entrypoints": {
    "client": [
      "vortex.client.vortexclient.client.VortexclientClient"
    ],
    "main": [
      "vortex.client.vortexclient.Vortexclient"
    ]
  },
  "mixins": [
    "vortexclient.mixins.json"
  ],
  "depends": {
    "fabricloader": ">=0.17.2",
    "minecraft": "1.16.5"
  }
}
